{"version": "1", "message": "ERROR: Hidden Testcases server unreachable.", "problem_id": "ads2_m3_a1_1", "user_id": "Ravikrishna234", "score": {"sample": {"0": {"execution_time": 0.16374850273132324, "passed": true}, "1": {"execution_time": 0.15897488594055176, "passed": true}, "2": {"execution_time": 0.15540122985839844, "passed": true}, "3": {"execution_time": 0.18238139152526855, "passed": true}, "4": {"execution_time": 0.1754617691040039, "passed": true}, "5": {"execution_time": 0.15625619888305664, "passed": true}, "6": {"execution_time": 0.1709456443786621, "passed": true}, "7": {"execution_time": 0.20720553398132324, "passed": true}}}, "check_style_score": "1/1"}